musicmood/__init__.py
musicmood/musicmood.py
musicmood-0.1.2.dist-info/DESCRIPTION.rst
musicmood-0.1.2.dist-info/METADATA
musicmood-0.1.2.dist-info/RECORD
musicmood-0.1.2.dist-info/WHEEL
musicmood-0.1.2.dist-info/entry_points.txt
musicmood-0.1.2.dist-info/metadata.json
musicmood-0.1.2.dist-info/top_level.txt
