Metadata-Version: 2.0
Name: musicmood
Version: 0.1.2
Summary: A python library for music recommendation based on mood classification
Home-page: https://github.com/BornFreeLabs/musicmood
Author: BornFree Labs
Author-email: bornfree@bornfreelabs.com
License: Apache Software License
Keywords: MachineLearning MusicRecommendation MoodClassification
Platform: UNKNOWN
Classifier: Development Status :: 1 - Planning
Classifier: Intended Audience :: Developers
Classifier: Topic :: Scientific/Engineering :: Artificial Intelligence
Classifier: License :: OSI Approved :: Apache Software License
Classifier: Programming Language :: Python :: 3
Classifier: Programming Language :: Python :: 3.3
Classifier: Programming Language :: Python :: 3.4
Classifier: Programming Language :: Python :: 3.5
Requires-Dist: numpy
Requires-Dist: pandas
Requires-Dist: scipy
Requires-Dist: sklearn
Provides-Extra: dev
Requires-Dist: check-manifest; extra == 'dev'
Provides-Extra: test
Requires-Dist: coverage; extra == 'test'
